mcqpy/__init__.py
mcqpy/cli/__init__.py
mcqpy/cli/autofill.py
mcqpy/cli/build.py
mcqpy/cli/check_latex.py
mcqpy/cli/config.py
mcqpy/cli/grade.py
mcqpy/cli/init.py
mcqpy/cli/main.py
mcqpy/cli/question/__init__.py
mcqpy/cli/question/init.py
mcqpy/cli/question/main.py
mcqpy/cli/question/render.py
mcqpy/cli/question/validate.py
mcqpy/compile/__init__.py
mcqpy/compile/front_config.py
mcqpy/compile/header_config.py
mcqpy/compile/latex_helpers.py
mcqpy/compile/latex_questions.py
mcqpy/compile/manifest.py
mcqpy/compile/mcq.py
mcqpy/compile/preamble.py
mcqpy/compile/solution_pdf.py
mcqpy/grade/__init__.py
mcqpy/grade/analysis.py
mcqpy/grade/grader.py
mcqpy/grade/parse_pdf.py
mcqpy/grade/rubric.py
mcqpy/grade/utils.py
mcqpy/question/__init__.py
mcqpy/question/filter/__init__.py
mcqpy/question/filter/base_filter.py
mcqpy/question/filter/date.py
mcqpy/question/filter/difficulty.py
mcqpy/question/filter/factory.py
mcqpy/question/filter/manifest.py
mcqpy/question/filter/slug.py
mcqpy/question/filter/stratified.py
mcqpy/question/filter/tag.py
mcqpy/question/question.py
mcqpy/question/question_bank.py
mcqpy/question/utils.py
mcqpy/utils/__init__.py
mcqpy/utils/check_latex.py
mcqpy/utils/fill_form.py
mcqpy/utils/image.py
mcqpy-0.2.3.dist-info/WHEEL
mcqpy-0.2.3.dist-info/entry_points.txt
mcqpy-0.2.3.dist-info/METADATA
mcqpy-0.2.3.dist-info/RECORD
