Metadata-Version: 2.3
Name: mcqpy
Version: 0.2.3
Summary: Multiple choice quiz generation and grading
Author: Mads-Peter
Author-email: Mads-Peter <machri@phys.au.dk>
Requires-Dist: click>=8.3.0
Requires-Dist: matplotlib>=3.10.7
Requires-Dist: numpy>=2.3.3
Requires-Dist: openpyxl>=3.1.5
Requires-Dist: pandas>=2.3.3
Requires-Dist: pillow>=11.3.0
Requires-Dist: pydantic>=2.12.0
Requires-Dist: pylatex>=1.4.2
Requires-Dist: pylatexenc>=2.10
Requires-Dist: pypdf>=6.1.1
Requires-Dist: pyyaml>=6.0.3
Requires-Dist: requests>=2.28.0
Requires-Dist: rich>=14.2.0
Requires-Dist: rich-click>=1.9.3
Requires-Python: >=3.13
